linestar/__init__.py
linestar/date_ids.json
linestar/helpers.py
linestar/standard.py
linestar/static/date_ids.json
linestar_scrape-1.0.9.dist-info/LICENSE
linestar_scrape-1.0.9.dist-info/METADATA
linestar_scrape-1.0.9.dist-info/WHEEL
linestar_scrape-1.0.9.dist-info/top_level.txt
linestar_scrape-1.0.9.dist-info/RECORD
