Metadata-Version: 2.1
Name: linestar-scrape
Version: 1.0.9
Summary: A package to scrape linestarapp.com daily fantasy sports ownership data
Home-page: https://github.com/WolverineSportsAnalytics/linestar-scrape
Author: Brendan Hart
Author-email: brendanahart@gmail.com
License: UNKNOWN
Platform: UNKNOWN
Classifier: Programming Language :: Python :: 3.6
Classifier: License :: OSI Approved :: MIT License
Classifier: Operating System :: OS Independent
